testevoo/__init__.py
testevoo/flightPrice_package.py
testevoo-0.0.1.dist-info/LICENSE
testevoo-0.0.1.dist-info/METADATA
testevoo-0.0.1.dist-info/WHEEL
testevoo-0.0.1.dist-info/top_level.txt
testevoo-0.0.1.dist-info/RECORD
