Metadata-Version: 2.1
Name: testevoo
Version: 0.0.1
Summary: Pacote para obter o menor preço de passagens aéreas
License: MIT
Keywords: flight,price,web scraping
License-File: LICENSE
Requires-Dist: selenium
Requires-Dist: Chorme
